FlashMHA/FlashMHA.py
FlashMHA/__init__.py
FlashMHA/attention.py
FlashMHA-0.6.3.dist-info/LICENSE
FlashMHA-0.6.3.dist-info/METADATA
FlashMHA-0.6.3.dist-info/WHEEL
FlashMHA-0.6.3.dist-info/top_level.txt
FlashMHA-0.6.3.dist-info/RECORD
