Metadata-Version: 2.1
Name: FlashMHA
Version: 0.6.3
Summary: FlashMHA - Pytorch
Home-page: https://github.com/kyegomez/FlashMHA
Author: Kye Gomez
Author-email: kye@apac.ai
License: MIT
Keywords: artificial intelligence,deep learning,optimizers,Prompt Engineering
Classifier: Development Status :: 4 - Beta
Classifier: Intended Audience :: Developers
Classifier: Topic :: Scientific/Engineering :: Artificial Intelligence
Classifier: License :: OSI Approved :: MIT License
Classifier: Programming Language :: Python :: 3.6
License-File: LICENSE
Requires-Dist: torch
Requires-Dist: einops
